moorkh/__init__.py
moorkh/normalize.py
moorkh/attacks/__init__.py
moorkh/attacks/base.py
moorkh/attacks/fgsm.py
moorkh/attacks/ifgsm.py
moorkh/attacks/noise.py
moorkh/attacks/pgd.py
moorkh/attacks/pgdl2.py
moorkh/attacks/rfgsm.py
moorkh/attacks/semantic.py
moorkh-0.0.2.dist-info/LICENSE
moorkh-0.0.2.dist-info/METADATA
moorkh-0.0.2.dist-info/WHEEL
moorkh-0.0.2.dist-info/top_level.txt
moorkh-0.0.2.dist-info/RECORD
