Metadata-Version: 2.1
Name: moorkh
Version: 0.0.2
Summary: Buddhu is a Adversarial examples generation library
Home-page: https://github.com/akshay-gupta123/moorkh
Author: Akshay Gupta
Author-email: akshay.bis2000@gmail.com
License: UNKNOWN
Project-URL: Bug Tracker, https://github.com/akshay-gupta123/moorkh/issues
Platform: UNKNOWN
Classifier: Programming Language :: Python :: 3
Classifier: License :: OSI Approved :: MIT License
Requires-Python: >=3.6
